{
  "comment": "自動推論では正確に決定できない科目のband/foundationGroupsを手動で補正するデータ。キーはナンバリング（科目コード）。",
  "overrides": {
    "BSC-1-B1-0204-002": {
      "name": "情報倫理と法",
      "foundationGroups": ["information"]
    },
    "BSC-1-B1-0204-003": {
      "name": "データサイエンス概論",
      "foundationGroups": ["mathematics"]
    },
    "BSC-1-B1-0204-004": {
      "name": "数学的思考とは何か",
      "foundationGroups": ["mathematics"]
    },
    "BSC-1-B1-0204-006": {
      "name": "現代社会とサイエンス",
      "foundationGroups": ["culture_thought"]
    },
    "BSC-1-B1-0204-009": {
      "name": "心理学",
      "foundationGroups": ["culture_thought"]
    },
    "BSC-1-B1-0204-011": {
      "name": "法学Ⅰ",
      "foundationGroups": ["society_network"]
    },
    "BSC-1-B1-0204-013": {
      "name": "企業経営",
      "foundationGroups": ["economy_market"]
    },
    "BSC-1-B1-0204-014": {
      "name": "地域アントレプレナーシップ",
      "foundationGroups": ["economy_market"]
    },
    "BSC-1-B1-0204-015": {
      "name": "地域課題の解決とイノベーション",
      "foundationGroups": ["economy_market"]
    },
    "BSC-1-B1-1030-001": {
      "name": "情報セキュリティ概論",
      "foundationGroups": ["information"]
    },
    "DIGI-1-B1-0204-003": {
      "name": "アニメ産業史",
      "foundationGroups": ["culture_thought"],
      "isDigitalIndustryHistoryEligible": true
    },
    "DIGI-1-B1-0204-004": {
      "name": "日本のゲーム産業史",
      "foundationGroups": ["culture_thought"],
      "isDigitalIndustryHistoryEligible": true
    },
    "DIGI-1-B1-1030-001": {
      "name": "IT産業史",
      "foundationGroups": ["information"],
      "isDigitalIndustryHistoryEligible": true
    },
    "DIGI-1-B1-1030-002": {
      "name": "マンガ産業史",
      "foundationGroups": ["culture_thought"],
      "isDigitalIndustryHistoryEligible": true
    },
    "BSC-1-A2-1234-016": {
      "name": "多言語ITコミュニケーション",
      "band": "foundation",
      "foundationGroups": ["multilingual_it_communication"]
    },
    "INT-1-A2-1234-005": {
      "name": "人工知能活用実践",
      "band": "introduction"
    },
    "PRJ-4-A3-1234-001": {
      "name": "プロジェクト実践",
      "band": "graduation_project",
      "isRequiredProjectPractice": true
    },
    "BSC-1-B1-1030-005": {
      "name": "数学史",
      "foundationGroups": ["mathematics"]
    },
    "BSC-1-B1-1030-007": {
      "name": "日本文学Ⅰ",
      "foundationGroups": ["culture_thought"]
    },
    "BSC-1-B1-1030-008": {
      "name": "文化人類学Ⅰ",
      "foundationGroups": ["culture_thought"]
    },
    "BSC-1-B1-1030-010": {
      "name": "社会学Ⅰ",
      "foundationGroups": ["society_network"]
    },
    "BSC-1-B1-1030-012": {
      "name": "伝わる論理とコミュニケーション",
      "foundationGroups": ["society_network"]
    }
  }
}
